rest_framework_gis/__init__.py
rest_framework_gis/apps.py
rest_framework_gis/fields.py
rest_framework_gis/filters.py
rest_framework_gis/filterset.py
rest_framework_gis/pagination.py
rest_framework_gis/schema.py
rest_framework_gis/serializers.py
rest_framework_gis/tilenames.py
djangorestframework_gis-1.1.dist-info/AUTHORS
djangorestframework_gis-1.1.dist-info/LICENSE
djangorestframework_gis-1.1.dist-info/METADATA
djangorestframework_gis-1.1.dist-info/WHEEL
djangorestframework_gis-1.1.dist-info/top_level.txt
djangorestframework_gis-1.1.dist-info/RECORD
