Metadata-Version: 2.1
Name: djangorestframework-gis
Version: 1.1
Summary: Geographic add-ons for Django Rest Framework
Home-page: https://github.com/openwisp/django-rest-framework-gis
Download-URL: https://github.com/openwisp/django-rest-framework-gis/releases
Author: Douglas Meehan
Author-email: django-rest-framework-gis@googlegroups.com
License: BSD
Project-URL: Bug Reports, https://github.com/openwisp/django-rest-framework-gis/issues
Project-URL: Continuous Integration, https://github.com/openwisp/django-rest-framework-gis/actions?query=workflow%3A%22Django+Rest+Framework+Gis+CI+Build%22
Project-URL: Mailing List, https://groups.google.com/forum/#!forum/django-rest-framework-gis
Project-URL: Code Coverage, https://coveralls.io/github/openwisp/django-rest-framework-gis
Project-URL: Source Code, https://github.com/openwisp/django-rest-framework-gis
Keywords: django,rest-framework,gis,geojson
Platform: Platform Indipendent
Classifier: Development Status :: 4 - Beta
Classifier: Environment :: Web Environment
Classifier: Topic :: Internet :: WWW/HTTP
Classifier: Intended Audience :: Developers
Classifier: License :: OSI Approved :: BSD License
Classifier: Operating System :: OS Independent
Classifier: Framework :: Django
Classifier: Programming Language :: Python
Classifier: Programming Language :: Python :: 3
Classifier: Programming Language :: Python :: 3.8
Classifier: Programming Language :: Python :: 3.9
Classifier: Programming Language :: Python :: 3.10
Classifier: Programming Language :: Python :: 3.11
Classifier: Programming Language :: Python :: 3.12
Classifier: Programming Language :: Python :: 3 :: Only
License-File: LICENSE
License-File: AUTHORS
Requires-Dist: djangorestframework<3.16,>=3.12
Requires-Dist: django-filter<25.0,>=23.5
